django_components/__init__.py
django_components/static/js/modal.js
django_components/static/js/popover.js
django_components/static/js/build/alert.js
django_components/static/js/build/image-slider.js
django_components/static/js/build/pagination.js
django_components/static/js/build/search.js
django_components/static/js/build/.module-cache/57bc5a1a0e215d87b097f80724cb3db3a3befe00.js
django_components/static/js/build/.module-cache/5bb08a404ee790c0ba3a9151cc9f9db947ff5291.js
django_components/static/js/build/.module-cache/8577b1d2d09056f7745928b339b45c8e6850e444.js
django_components/static/js/build/.module-cache/bcb712d5bb9614dd2958c85cea4a6737d73de6cf.js
django_components/static/js/src/alert.js
django_components/static/js/src/image-slider.js
django_components/static/js/src/pagination.js
django_components/static/js/src/search.js
django_components/templates/accordian.html
django_components/templates/alert.html
django_components/templates/component_css.html
django_components/templates/CustomSearch.html
django_components/templates/image-slider.html
django_components/templates/modal.html
django_components/templates/pagination.html
django_components/templates/popover.html
django_components/templates/react_data.html
django_components/templates/server-pagination.html
django_components/templates/vanilla_data.html
django_components/templatetags/__init__.py
django_components/templatetags/components.py
DjangoComponents-0.0.0.33.dist-info/DESCRIPTION.rst
DjangoComponents-0.0.0.33.dist-info/METADATA
DjangoComponents-0.0.0.33.dist-info/metadata.json
DjangoComponents-0.0.0.33.dist-info/RECORD
DjangoComponents-0.0.0.33.dist-info/top_level.txt
DjangoComponents-0.0.0.33.dist-info/WHEEL
