Metadata-Version: 2.0
Name: DjangoComponents
Version: 0.0.0.33
Summary: Package of reusable Django components
Home-page: UNKNOWN
Author: Lightning Kite
Author-email: UNKNOWN
License: UNKNOWN
Keywords: django components reusable
Platform: UNKNOWN
Classifier: Development Status :: 3 - Alpha
Classifier: Intended Audience :: Developers
Classifier: Topic :: Software Development :: Build Tools
Classifier: License :: OSI Approved :: MIT License
Classifier: Programming Language :: Python :: 2
Classifier: Programming Language :: Python :: 2.6
Classifier: Programming Language :: Python :: 2.7
Classifier: Programming Language :: Python :: 3
Classifier: Programming Language :: Python :: 3.2
Classifier: Programming Language :: Python :: 3.3
Classifier: Programming Language :: Python :: 3.4
